pycronic/__init__.py
pycronic/constants.py
pycronic-0.0.5.data/scripts/cronic
pycronic-0.0.5.dist-info/LICENSE
pycronic-0.0.5.dist-info/METADATA
pycronic-0.0.5.dist-info/WHEEL
pycronic-0.0.5.dist-info/top_level.txt
pycronic-0.0.5.dist-info/RECORD
