Metadata-Version: 2.1
Name: pycronic
Version: 0.0.5
Summary: A crontab script wrapper written by python
Home-page: https://github.com/piglei/pycronic/
Author: piglei
Author-email: piglei2007@gmail.com
License: GPL
Keywords: crontab cronic
Platform: UNKNOWN
Classifier: Programming Language :: Python :: 3
Classifier: Programming Language :: Python :: 2.7
Requires-Dist: configobj
Requires-Dist: sender
